[{"fecha":"2014-01-01","cod":"0303890090","label":"Desconocido","sector":"游붏 Pesca","fob":22.6875,"cif":0,"peso":24.9},{"fecha":"2014-01-01","cod":"0306160000","label":"Camarones y langostinos y dem치s dec치podos natantia de agua fr칤a","sector":"游붏 Pesca","fob":1495.224,"cif":0,"peso":158.908},{"fecha":"2014-01-01","cod":"0306171100","label":"Enteros","sector":"游붏 Pesca","fob":317.25,"cif":0,"peso":47.0},{"fecha":"2014-01-01","cod":"0306171300","label":"Colas con caparaz칩n, sin cocer en agua o vapor","sector":"游붏 Pesca","fob":1207.528,"cif":0,"peso":119.80273},{"fecha":"2014-01-01","cod":"0306171900","label":"Desconocido","sector":"游붏 Pesca","fob":489.60943,"cif":0,"peso":46.278},{"fecha":"2014-01-01","cod":"0306179900","label":"Desconocido","sector":"游붏 Pesca","fob":3617.74469,"cif":0,"peso":341.83851},{"fecha":"2014-01-01","cod":"0511919000","label":"Desconocido","sector":"游닍 Otros","fob":54.08,"cif":0,"peso":104.0},{"fecha":"2014-01-01","cod":"0603110000","label":"Rosas","sector":"游닍 Otros","fob":150.53691,"cif":0,"peso":20.69603},{"fecha":"2014-01-01","cod":"0603129000","label":"Desconocido","sector":"游닍 Otros","fob":0.4004,"cif":0,"peso":0.0585},{"fecha":"2014-01-01","cod":"0603199090","label":"Desconocido","sector":"游닍 Otros","fob":0.4496,"cif":0,"peso":0.1423},{"fecha":"2014-01-01","cod":"0603900000","label":"Desconocido","sector":"游닍 Otros","fob":37.134,"cif":0,"peso":0.85575},{"fecha":"2014-01-01","cod":"0803901100","label":"Tipo 춺cavendish valery췉","sector":"游꼛 Frutas","fob":5230.47077,"cif":0,"peso":10241.94518},{"fecha":"2014-01-01","cod":"0803901200","label":"Bocadillo","sector":"游꼛 Frutas","fob":32.20352,"cif":0,"peso":42.9984},{"fecha":"2014-01-01","cod":"0811909900","label":"Desconocido","sector":"游꼛 Frutas","fob":20.515,"cif":0,"peso":24.0},{"fecha":"2014-01-01","cod":"1212999000","label":"Desconocido","sector":"游닍 Otros","fob":147.48496,"cif":0,"peso":68.04642},{"fecha":"2014-01-01","cod":"1801001900","label":"Desconocido","sector":"游꼶 Cacao","fob":1065.53067,"cif":0,"peso":400.2},{"fecha":"2014-01-01","cod":"2007999200","label":"Pur칠s y pastas","sector":"游닍 Otros","fob":139.12,"cif":0,"peso":244.0},{"fecha":"2014-01-01","cod":"2009892000","label":"De maracuy치","sector":"游닍 Otros","fob":282.40705,"cif":0,"peso":25.0},{"fecha":"2014-01-01","cod":"2301201100","label":"Con un contenido de grasa superior a 2% en peso","sector":"游닍 Otros","fob":2197.83193,"cif":0,"peso":1620.791},{"fecha":"2014-01-01","cod":"2603000000","label":"Minerales de cobre y sus concentrados.","sector":"游닍 Otros","fob":623.13305,"cif":0,"peso":351.14},{"fecha":"2014-01-01","cod":"2616901000","label":"Minerales de oro y sus concentrados","sector":"游닍 Otros","fob":2388.34124,"cif":0,"peso":1922.101},{"fecha":"2014-01-01","cod":"2844409000","label":"Desconocido","sector":"游닍 Otros","fob":22.6,"cif":0,"peso":0.1},{"fecha":"2014-01-01","cod":"3915900000","label":"De los dem치s pl치sticos","sector":"游빖 Pl치sticos","fob":137.5165,"cif":0,"peso":271.203},{"fecha":"2014-01-01","cod":"3921199000","label":"Desconocido","sector":"游빖 Pl치sticos","fob":9.0,"cif":0,"peso":50.0},{"fecha":"2014-01-01","cod":"4102100000","label":"Con lana","sector":"游닍 Otros","fob":72.0,"cif":0,"peso":120.0},{"fecha":"2014-01-01","cod":"4407220000","label":"Virola, imbuia y balsa","sector":"游뿻 Madera","fob":611.7684,"cif":0,"peso":217.94286},{"fecha":"2014-01-01","cod":"4407990000","label":"Desconocido","sector":"游뿻 Madera","fob":16.89264,"cif":0,"peso":75.56},{"fecha":"2014-01-01","cod":"4413000000","label":"Madera densificada en bloques, tablas, tiras o perfiles.","sector":"游뿻 Madera","fob":15.46,"cif":0,"peso":169.4},{"fecha":"2014-01-01","cod":"7403220000","label":"A base de cobreesta침o","sector":"游닍 Otros","fob":204.8139,"cif":0,"peso":44.046},{"fecha":"2014-01-01","cod":"7404000000","label":"Desperdicios y desechos, de cobre.","sector":"游닍 Otros","fob":3056.24641,"cif":0,"peso":569.986},{"fecha":"2014-01-01","cod":"7602000000","label":"Desperdicios y desechos, de aluminio.","sector":"游닍 Otros","fob":308.8633,"cif":0,"peso":257.051},{"fecha":"2014-01-01","cod":"8477100000","label":"M치quinas de moldear por inyecci칩n","sector":"丘뙖잺 Maquinaria","fob":25.0,"cif":0,"peso":17.5},{"fecha":"2014-02-01","cod":"0303340000","label":"Rodaballos","sector":"游붏 Pesca","fob":325.9088,"cif":0,"peso":161.53},{"fecha":"2014-02-01","cod":"0303390000","label":"Desconocido","sector":"游붏 Pesca","fob":89.75383,"cif":0,"peso":50.41},{"fecha":"2014-02-01","cod":"0303690000","label":"Desconocido","sector":"游붏 Pesca","fob":70.8,"cif":0,"peso":27.0},{"fecha":"2014-02-01","cod":"0304890000","label":"Desconocido","sector":"游붏 Pesca","fob":2.50827,"cif":0,"peso":3.59},{"fecha":"2014-02-01","cod":"0306160000","label":"Camarones y langostinos y dem치s dec치podos natantia de agua fr칤a","sector":"游붏 Pesca","fob":1512.89347,"cif":0,"peso":142.8668},{"fecha":"2014-02-01","cod":"0306171300","label":"Colas con caparaz칩n, sin cocer en agua o vapor","sector":"游붏 Pesca","fob":395.91,"cif":0,"peso":36.28736},{"fecha":"2014-02-01","cod":"0306171900","label":"Desconocido","sector":"游붏 Pesca","fob":2070.44619,"cif":0,"peso":211.872},{"fecha":"2014-02-01","cod":"0306179900","label":"Desconocido","sector":"游붏 Pesca","fob":4982.40448,"cif":0,"peso":469.65664},{"fecha":"2014-02-01","cod":"0511912000","label":"Despojos de pescado, no comestibles","sector":"游닍 Otros","fob":18.59,"cif":0,"peso":13.0},{"fecha":"2014-02-01","cod":"0511919000","label":"Desconocido","sector":"游닍 Otros","fob":39.52,"cif":0,"peso":76.0},{"fecha":"2014-02-01","cod":"0603110000","label":"Rosas","sector":"游닍 Otros","fob":224.71381,"cif":0,"peso":21.32762},{"fecha":"2014-02-01","cod":"0603199090","label":"Desconocido","sector":"游닍 Otros","fob":1.1096,"cif":0,"peso":0.0832},{"fecha":"2014-02-01","cod":"0603900000","label":"Desconocido","sector":"游닍 Otros","fob":7.1856,"cif":0,"peso":0.156},{"fecha":"2014-02-01","cod":"0803901100","label":"Tipo 춺cavendish valery췉","sector":"游꼛 Frutas","fob":4600.86306,"cif":0,"peso":8917.50996},{"fecha":"2014-02-01","cod":"0803901200","label":"Bocadillo","sector":"游꼛 Frutas","fob":89.02528,"cif":0,"peso":116.9056},{"fecha":"2014-02-01","cod":"1212999000","label":"Desconocido","sector":"游닍 Otros","fob":55.5203,"cif":0,"peso":25.3518},{"fecha":"2014-02-01","cod":"1520000000","label":"Glicerol en bruto; aguas y lej칤as glicerinosas.","sector":"游닍 Otros","fob":149.69818,"cif":0,"peso":494.87},{"fecha":"2014-02-01","cod":"2007999200","label":"Pur칠s y pastas","sector":"游닍 Otros","fob":73.52,"cif":0,"peso":104.0},{"fecha":"2014-02-01","cod":"2301201100","label":"Con un contenido de grasa superior a 2% en peso","sector":"游닍 Otros","fob":4685.67528,"cif":0,"peso":3392.582},{"fecha":"2014-02-01","cod":"2603000000","label":"Minerales de cobre y sus concentrados.","sector":"游닍 Otros","fob":643.69549,"cif":0,"peso":380.155},{"fecha":"2014-02-01","cod":"2616901000","label":"Minerales de oro y sus concentrados","sector":"游닍 Otros","fob":2416.48569,"cif":0,"peso":2052.996},{"fecha":"2014-02-01","cod":"3903190000","label":"Desconocido","sector":"游빖 Pl치sticos","fob":28.13,"cif":0,"peso":50.73},{"fecha":"2014-02-01","cod":"3915900000","label":"De los dem치s pl치sticos","sector":"游빖 Pl치sticos","fob":609.12408,"cif":0,"peso":1160.299},{"fecha":"2014-02-01","cod":"3921199000","label":"Desconocido","sector":"游빖 Pl치sticos","fob":8.69382,"cif":0,"peso":48.299},{"fecha":"2014-02-01","cod":"3926909000","label":"Desconocido","sector":"游빖 Pl치sticos","fob":0.001,"cif":0,"peso":0.002},{"fecha":"2014-02-01","cod":"4403490000","label":"Desconocido","sector":"游뿻 Madera","fob":9.91316,"cif":0,"peso":102.56},{"fecha":"2014-02-01","cod":"4403990000","label":"Desconocido","sector":"游뿻 Madera","fob":5.86938,"cif":0,"peso":73.89},{"fecha":"2014-02-01","cod":"4407220000","label":"Virola, imbuia y balsa","sector":"游뿻 Madera","fob":657.37101,"cif":0,"peso":250.30807},{"fecha":"2014-02-01","cod":"4819200000","label":"Cajas y cartonajes, plegables, de papel o cart칩n, sin corrugar","sector":"游닍 Otros","fob":0.004,"cif":0,"peso":0.02},{"fecha":"2014-02-01","cod":"7403220000","label":"A base de cobreesta침o","sector":"游닍 Otros","fob":325.7616,"cif":0,"peso":70.1},{"fecha":"2014-02-01","cod":"7404000000","label":"Desperdicios y desechos, de cobre.","sector":"游닍 Otros","fob":3452.9911,"cif":0,"peso":582.301},{"fecha":"2014-02-01","cod":"7602000000","label":"Desperdicios y desechos, de aluminio.","sector":"游닍 Otros","fob":416.18493,"cif":0,"peso":326.832},{"fecha":"2014-02-01","cod":"8481909000","label":"Desconocido","sector":"丘뙖잺 Maquinaria","fob":15.08711,"cif":0,"peso":0.285},{"fecha":"2014-02-01","cod":"9606301000","label":"De pl치stico o de tagua","sector":"游닍 Otros","fob":181.0,"cif":0,"peso":20.3},{"fecha":"2014-03-01","cod":"0303340000","label":"Rodaballos","sector":"游붏 Pesca","fob":116.265,"cif":0,"peso":54.0},{"fecha":"2014-03-01","cod":"0303690000","label":"Desconocido","sector":"游붏 Pesca","fob":70.444,"cif":0,"peso":26.23},{"fecha":"2014-03-01","cod":"0303890090","label":"Desconocido","sector":"游붏 Pesca","fob":61.446,"cif":0,"peso":25.0},{"fecha":"2014-03-01","cod":"0306160000","label":"Camarones y langostinos y dem치s dec치podos natantia de agua fr칤a","sector":"游붏 Pesca","fob":1271.3094,"cif":0,"peso":114.014},{"fecha":"2014-03-01","cod":"0306171100","label":"Enteros","sector":"游붏 Pesca","fob":399.65,"cif":0,"peso":47.0},{"fecha":"2014-03-01","cod":"0306171300","label":"Colas con caparaz칩n, sin cocer en agua o vapor","sector":"游붏 Pesca","fob":884.394,"cif":0,"peso":78.03597},{"fecha":"2014-03-01","cod":"0306171900","label":"Desconocido","sector":"游붏 Pesca","fob":1300.3852,"cif":0,"peso":144.12},{"fecha":"2014-03-01","cod":"0306179900","label":"Desconocido","sector":"游붏 Pesca","fob":5830.73131,"cif":0,"peso":595.74427},{"fecha":"2014-03-01","cod":"0511919000","label":"Desconocido","sector":"游닍 Otros","fob":40.56,"cif":0,"peso":78.0},{"fecha":"2014-03-01","cod":"0603110000","label":"Rosas","sector":"游닍 Otros","fob":45.67135,"cif":0,"peso":5.94119},{"fecha":"2014-03-01","cod":"0603129000","label":"Desconocido","sector":"游닍 Otros","fob":0.78656,"cif":0,"peso":0.111},{"fecha":"2014-03-01","cod":"0603199090","label":"Desconocido","sector":"游닍 Otros","fob":0.69328,"cif":0,"peso":0.051},{"fecha":"2014-03-01","cod":"0603900000","label":"Desconocido","sector":"游닍 Otros","fob":55.12894,"cif":0,"peso":1.1049},{"fecha":"2014-03-01","cod":"0803901100","label":"Tipo 춺cavendish valery췉","sector":"游꼛 Frutas","fob":3549.15204,"cif":0,"peso":7246.63777},{"fecha":"2014-03-01","cod":"0803901200","label":"Bocadillo","sector":"游꼛 Frutas","fob":55.2768,"cif":0,"peso":67.5168},{"fecha":"2014-03-01","cod":"1520000000","label":"Glicerol en bruto; aguas y lej칤as glicerinosas.","sector":"游닍 Otros","fob":73.13464,"cif":0,"peso":224.14},{"fecha":"2014-03-01","cod":"1801001900","label":"Desconocido","sector":"游꼶 Cacao","fob":150.71735,"cif":0,"peso":50.025},{"fecha":"2014-03-01","cod":"2007999200","label":"Pur칠s y pastas","sector":"游닍 Otros","fob":5.50935,"cif":0,"peso":10.017},{"fecha":"2014-03-01","cod":"2301201100","label":"Con un contenido de grasa superior a 2% en peso","sector":"游닍 Otros","fob":2603.99659,"cif":0,"peso":1833.948},{"fecha":"2014-03-01","cod":"2603000000","label":"Minerales de cobre y sus concentrados.","sector":"游닍 Otros","fob":777.41112,"cif":0,"peso":626.186},{"fecha":"2014-03-01","cod":"2616901000","label":"Minerales de oro y sus concentrados","sector":"游닍 Otros","fob":2968.98756,"cif":0,"peso":2525.088},{"fecha":"2014-03-01","cod":"2710192200","label":"Fueloils","sector":"游닍 Otros","fob":634.0,"cif":0,"peso":1000.0},{"fecha":"2014-03-01","cod":"3915900000","label":"De los dem치s pl치sticos","sector":"游빖 Pl치sticos","fob":526.13211,"cif":0,"peso":975.837},{"fecha":"2014-03-01","cod":"3923109000","label":"Desconocido","sector":"游빖 Pl치sticos","fob":0.17202,"cif":0,"peso":0.003},{"fecha":"2014-03-01","cod":"3923309900","label":"Desconocido","sector":"游빖 Pl치sticos","fob":0.02432,"cif":0,"peso":0.0054},{"fecha":"2014-03-01","cod":"4407220000","label":"Virola, imbuia y balsa","sector":"游뿻 Madera","fob":2257.23064,"cif":0,"peso":723.12004},{"fecha":"2014-03-01","cod":"6504000000","label":"Sombreros y dem치s tocados, trenzados o fabricados por uni칩n de tiras de cualquier materia, incluso guarnecidos.","sector":"游닍 Otros","fob":13.0188,"cif":0,"peso":0.04185},{"fecha":"2014-03-01","cod":"7310299000","label":"Desconocido","sector":"游닍 Otros","fob":0.0358,"cif":0,"peso":0.0054},{"fecha":"2014-03-01","cod":"7403220000","label":"A base de cobreesta침o","sector":"游닍 Otros","fob":540.02002,"cif":0,"peso":117.094},{"fecha":"2014-03-01","cod":"7404000000","label":"Desperdicios y desechos, de cobre.","sector":"游닍 Otros","fob":3092.52316,"cif":0,"peso":552.432},{"fecha":"2014-03-01","cod":"7419999000","label":"Desconocido","sector":"游닍 Otros","fob":0.1105,"cif":0,"peso":0.02},{"fecha":"2014-03-01","cod":"7602000000","label":"Desperdicios y desechos, de aluminio.","sector":"游닍 Otros","fob":159.22832,"cif":0,"peso":126.775},{"fecha":"2014-03-01","cod":"8301401000","label":"Para cajas de caudales","sector":"游닍 Otros","fob":2.25,"cif":0,"peso":0.553},{"fecha":"2014-03-01","cod":"8309900000","label":"Desconocido","sector":"游닍 Otros","fob":0.002,"cif":0,"peso":0.0054},{"fecha":"2014-03-01","cod":"8413920000","label":"De elevadores de l칤quidos","sector":"丘뙖잺 Maquinaria","fob":13.6289,"cif":0,"peso":1.942},{"fecha":"2014-03-01","cod":"8414590000","label":"Desconocido","sector":"丘뙖잺 Maquinaria","fob":2.4492,"cif":0,"peso":0.008},{"fecha":"2014-03-01","cod":"8504409000","label":"Desconocido","sector":"游댋 El칠ctrico","fob":14.49,"cif":0,"peso":0.18},{"fecha":"2014-03-01","cod":"8517700000","label":"Partes","sector":"游댋 El칠ctrico","fob":0.25353,"cif":0,"peso":0.0061},{"fecha":"2014-03-01","cod":"8519899000","label":"Desconocido","sector":"游댋 El칠ctrico","fob":9.72258,"cif":0,"peso":0.28},{"fecha":"2014-03-01","cod":"8544422000","label":", de cobre","sector":"游댋 El칠ctrico","fob":0.3708,"cif":0,"peso":0.117},{"fecha":"2014-03-01","cod":"9031809000","label":"Desconocido","sector":"游닍 Otros","fob":1.39845,"cif":0,"peso":0.028},{"fecha":"2014-04-01","cod":"0303340000","label":"Rodaballos","sector":"游붏 Pesca","fob":426.09714,"cif":0,"peso":212.29},{"fecha":"2014-04-01","cod":"0303390000","label":"Desconocido","sector":"游붏 Pesca","fob":7.01086,"cif":0,"peso":3.71},{"fecha":"2014-04-01","cod":"0303890090","label":"Desconocido","sector":"游붏 Pesca","fob":66.53386,"cif":0,"peso":26.9},{"fecha":"2014-04-01","cod":"0306160000","label":"Camarones y langostinos y dem치s dec치podos natantia de agua fr칤a","sector":"游붏 Pesca","fob":701.3375,"cif":0,"peso":68.04},{"fecha":"2014-04-01","cod":"0306171900","label":"Desconocido","sector":"游붏 Pesca","fob":1233.8204,"cif":0,"peso":144.6},{"fecha":"2014-04-01","cod":"0306179100","label":"Camarones de r칤o de los g칠neros macrobrachium","sector":"游붏 Pesca","fob":235.4121,"cif":0,"peso":22.57552},{"fecha":"2014-04-01","cod":"0306179900","label":"Desconocido","sector":"游붏 Pesca","fob":2582.11295,"cif":0,"peso":288.41522},{"fecha":"2014-04-01","cod":"0511912000","label":"Despojos de pescado, no comestibles","sector":"游닍 Otros","fob":18.59,"cif":0,"peso":13.0},{"fecha":"2014-04-01","cod":"0511919000","label":"Desconocido","sector":"游닍 Otros","fob":40.56,"cif":0,"peso":78.0},{"fecha":"2014-04-01","cod":"0603110000","label":"Rosas","sector":"游닍 Otros","fob":41.015,"cif":0,"peso":5.27913},{"fecha":"2014-04-01","cod":"0603129000","label":"Desconocido","sector":"游닍 Otros","fob":1.2199,"cif":0,"peso":0.3375},{"fecha":"2014-04-01","cod":"0603199090","label":"Desconocido","sector":"游닍 Otros","fob":0.6736,"cif":0,"peso":0.10595},{"fecha":"2014-04-01","cod":"0603900000","label":"Desconocido","sector":"游닍 Otros","fob":80.66664,"cif":0,"peso":1.10315},{"fecha":"2014-04-01","cod":"0803901100","label":"Tipo 춺cavendish valery췉","sector":"游꼛 Frutas","fob":8520.57988,"cif":0,"peso":18474.2017},{"fecha":"2014-04-01","cod":"0803901200","label":"Bocadillo","sector":"游꼛 Frutas","fob":166.3548,"cif":0,"peso":224.4},{"fecha":"2014-04-01","cod":"0811909900","label":"Desconocido","sector":"游꼛 Frutas","fob":40.675,"cif":0,"peso":48.0},{"fecha":"2014-04-01","cod":"1211909000","label":"Desconocido","sector":"游닍 Otros","fob":55.5203,"cif":0,"peso":24.8932},{"fecha":"2014-04-01","cod":"1404909000","label":"Desconocido","sector":"游닍 Otros","fob":24.28,"cif":0,"peso":20.0},{"fecha":"2014-04-01","cod":"1801001900","label":"Desconocido","sector":"游꼶 Cacao","fob":564.35099,"cif":0,"peso":200.1},{"fecha":"2014-04-01","cod":"1803100000","label":"Sin desgrasar","sector":"游꼶 Cacao","fob":0.008,"cif":0,"peso":0.016},{"fecha":"2014-04-01","cod":"2007999200","label":"Pur칠s y pastas","sector":"游닍 Otros","fob":44.8,"cif":0,"peso":80.0},{"fecha":"2014-04-01","cod":"2009892000","label":"De maracuy치","sector":"游닍 Otros","fob":269.70356,"cif":0,"peso":25.0},{"fecha":"2014-04-01","cod":"2301201100","label":"Con un contenido de grasa superior a 2% en peso","sector":"游닍 Otros","fob":582.15826,"cif":0,"peso":413.643},{"fecha":"2014-04-01","cod":"2603000000","label":"Minerales de cobre y sus concentrados.","sector":"游닍 Otros","fob":1244.61291,"cif":0,"peso":1122.312},{"fecha":"2014-04-01","cod":"2616901000","label":"Minerales de oro y sus concentrados","sector":"游닍 Otros","fob":1311.48708,"cif":0,"peso":1089.314},{"fecha":"2014-04-01","cod":"3915900000","label":"De los dem치s pl치sticos","sector":"游빖 Pl치sticos","fob":473.38794,"cif":0,"peso":849.473},{"fecha":"2014-04-01","cod":"3921199000","label":"Desconocido","sector":"游빖 Pl치sticos","fob":17.6013,"cif":0,"peso":97.785},{"fecha":"2014-04-01","cod":"4407220000","label":"Virola, imbuia y balsa","sector":"游뿻 Madera","fob":2673.32483,"cif":0,"peso":794.74598},{"fecha":"2014-04-01","cod":"4407290000","label":"Desconocido","sector":"游뿻 Madera","fob":11.6,"cif":0,"peso":15.32},{"fecha":"2014-04-01","cod":"4413000000","label":"Madera densificada en bloques, tablas, tiras o perfiles.","sector":"游뿻 Madera","fob":1.8711,"cif":0,"peso":24.2},{"fecha":"2014-04-01","cod":"5305001100","label":"En bruto","sector":"游닍 Otros","fob":202.5,"cif":0,"peso":150.0},{"fecha":"2014-04-01","cod":"7403220000","label":"A base de cobreesta침o","sector":"游닍 Otros","fob":564.93749,"cif":0,"peso":137.775},{"fecha":"2014-04-01","cod":"7404000000","label":"Desperdicios y desechos, de cobre.","sector":"游닍 Otros","fob":1879.2935,"cif":0,"peso":346.421},{"fecha":"2014-04-01","cod":"7602000000","label":"Desperdicios y desechos, de aluminio.","sector":"游닍 Otros","fob":166.3767,"cif":0,"peso":168.755},{"fecha":"2014-04-01","cod":"8301401000","label":"Para cajas de caudales","sector":"游닍 Otros","fob":2.25,"cif":0,"peso":0.56},{"fecha":"2014-04-01","cod":"9606301000","label":"De pl치stico o de tagua","sector":"游닍 Otros","fob":287.9943,"cif":0,"peso":28.24485},{"fecha":"2014-05-01","cod":"0303390000","label":"Desconocido","sector":"游붏 Pesca","fob":52.755,"cif":0,"peso":27.0},{"fecha":"2014-05-01","cod":"0303690000","label":"Desconocido","sector":"游붏 Pesca","fob":21.6,"cif":0,"peso":27.0},{"fecha":"2014-05-01","cod":"0303890090","label":"Desconocido","sector":"游붏 Pesca","fob":53.061,"cif":0,"peso":27.0},{"fecha":"2014-05-01","cod":"0306160000","label":"Camarones y langostinos y dem치s dec치podos natantia de agua fr칤a","sector":"游붏 Pesca","fob":777.0145,"cif":0,"peso":90.71923},{"fecha":"2014-05-01","cod":"0306171100","label":"Enteros","sector":"游붏 Pesca","fob":173.28,"cif":0,"peso":24.0},{"fecha":"2014-05-01","cod":"0306171900","label":"Desconocido","sector":"游붏 Pesca","fob":1388.40635,"cif":0,"peso":187.1024},{"fecha":"2014-05-01","cod":"0306179900","label":"Desconocido","sector":"游붏 Pesca","fob":2269.4191,"cif":0,"peso":221.59032},{"fecha":"2014-05-01","cod":"0511919000","label":"Desconocido","sector":"游닍 Otros","fob":0.64,"cif":0,"peso":0.06},{"fecha":"2014-05-01","cod":"0603110000","label":"Rosas","sector":"游닍 Otros","fob":49.14493,"cif":0,"peso":6.30378},{"fecha":"2014-05-01","cod":"0603129000","label":"Desconocido","sector":"游닍 Otros","fob":0.7335,"cif":0,"peso":0.0855},{"fecha":"2014-05-01","cod":"0603199090","label":"Desconocido","sector":"游닍 Otros","fob":0.3731,"cif":0,"peso":0.07},{"fecha":"2014-05-01","cod":"0603900000","label":"Desconocido","sector":"游닍 Otros","fob":9.138,"cif":0,"peso":0.25415},{"fecha":"2014-05-01","cod":"0803901100","label":"Tipo 춺cavendish valery췉","sector":"游꼛 Frutas","fob":10088.52262,"cif":0,"peso":22946.87641},{"fecha":"2014-05-01","cod":"0803901200","label":"Bocadillo","sector":"游꼛 Frutas","fob":109.082,"cif":0,"peso":146.55},{"fecha":"2014-05-01","cod":"0811909900","label":"Desconocido","sector":"游꼛 Frutas","fob":20.515,"cif":0,"peso":24.0},{"fecha":"2014-05-01","cod":"1212999000","label":"Desconocido","sector":"游닍 Otros","fob":53.14056,"cif":0,"peso":24.1548},{"fecha":"2014-05-01","cod":"1404909000","label":"Desconocido","sector":"游닍 Otros","fob":7.04,"cif":0,"peso":22.0},{"fecha":"2014-05-01","cod":"1801001900","label":"Desconocido","sector":"游꼶 Cacao","fob":397.85383,"cif":0,"peso":150.075},{"fecha":"2014-05-01","cod":"2007999200","label":"Pur칠s y pastas","sector":"游닍 Otros","fob":98.176,"cif":0,"peso":140.8},{"fecha":"2014-05-01","cod":"2009891000","label":"De papaya","sector":"游닍 Otros","fob":54.868,"cif":0,"peso":18.92},{"fecha":"2014-05-01","cod":"2204210000","label":"En recipientes con capacidad inferior o igual a 2 l","sector":"游닍 Otros","fob":57.0,"cif":0,"peso":45.0},{"fecha":"2014-05-01","cod":"2301201100","label":"Con un contenido de grasa superior a 2% en peso","sector":"游닍 Otros","fob":1578.84004,"cif":0,"peso":1034.952},{"fecha":"2014-05-01","cod":"2301209000","label":"Desconocido","sector":"游닍 Otros","fob":48.0012,"cif":0,"peso":53.04},{"fecha":"2014-05-01","cod":"2309901000","label":"Preparaciones forrajeras con adici칩n de melazas o de az칰car","sector":"游닍 Otros","fob":41.4,"cif":0,"peso":9.0},{"fecha":"2014-05-01","cod":"2603000000","label":"Minerales de cobre y sus concentrados.","sector":"游닍 Otros","fob":709.44682,"cif":0,"peso":509.051},{"fecha":"2014-05-01","cod":"2616901000","label":"Minerales de oro y sus concentrados","sector":"游닍 Otros","fob":3403.09033,"cif":0,"peso":3339.501},{"fecha":"2014-05-01","cod":"2621900000","label":"Desconocido","sector":"游닍 Otros","fob":0.0005,"cif":0,"peso":0.05},{"fecha":"2014-05-01","cod":"3214900000","label":"Desconocido","sector":"游닍 Otros","fob":0.0005,"cif":0,"peso":0.05},{"fecha":"2014-05-01","cod":"3915900000","label":"De los dem치s pl치sticos","sector":"游빖 Pl치sticos","fob":394.11142,"cif":0,"peso":730.652},{"fecha":"2014-05-01","cod":"3921199000","label":"Desconocido","sector":"游빖 Pl치sticos","fob":12.1275,"cif":0,"peso":67.375},{"fecha":"2014-05-01","cod":"4403990000","label":"Desconocido","sector":"游뿻 Madera","fob":20.0783,"cif":0,"peso":195.89},{"fecha":"2014-05-01","cod":"4407220000","label":"Virola, imbuia y balsa","sector":"游뿻 Madera","fob":2376.46449,"cif":0,"peso":664.55092},{"fecha":"2014-05-01","cod":"4407290000","label":"Desconocido","sector":"游뿻 Madera","fob":7.17174,"cif":0,"peso":1.973},{"fecha":"2014-05-01","cod":"4413000000","label":"Madera densificada en bloques, tablas, tiras o perfiles.","sector":"游뿻 Madera","fob":3.7104,"cif":0,"peso":72.55},{"fecha":"2014-05-01","cod":"5305001100","label":"En bruto","sector":"游닍 Otros","fob":65.5,"cif":0,"peso":50.0},{"fecha":"2014-05-01","cod":"6502001000","label":"De paja toquilla o de paja mocora","sector":"游닍 Otros","fob":0.84,"cif":0,"peso":0.005},{"fecha":"2014-05-01","cod":"6504000000","label":"Sombreros y dem치s tocados, trenzados o fabricados por uni칩n de tiras de cualquier materia, incluso guarnecidos.","sector":"游닍 Otros","fob":2.372,"cif":0,"peso":0.0085},{"fecha":"2014-05-01","cod":"7403220000","label":"A base de cobreesta침o","sector":"游닍 Otros","fob":193.68026,"cif":0,"peso":45.677},{"fecha":"2014-05-01","cod":"7404000000","label":"Desperdicios y desechos, de cobre.","sector":"游닍 Otros","fob":1831.67512,"cif":0,"peso":413.946},{"fecha":"2014-05-01","cod":"7602000000","label":"Desperdicios y desechos, de aluminio.","sector":"游닍 Otros","fob":257.15621,"cif":0,"peso":203.048},{"fecha":"2014-05-01","cod":"8301409000","label":"Desconocido","sector":"游닍 Otros","fob":15.0,"cif":0,"peso":0.562},{"fecha":"2014-05-01","cod":"8431439000","label":"Desconocido","sector":"丘뙖잺 Maquinaria","fob":10.92512,"cif":0,"peso":0.149},{"fecha":"2014-05-01","cod":"8708939100","label":"Platos  y discos","sector":"游뚱 Veh칤culos","fob":4.00373,"cif":0,"peso":1.1},{"fecha":"2014-05-01","cod":"8708939900","label":"Desconocido","sector":"游뚱 Veh칤culos","fob":2.57834,"cif":0,"peso":0.5},{"fecha":"2014-05-01","cod":"9013809000","label":"Desconocido","sector":"游닍 Otros","fob":5.0,"cif":0,"peso":0.048},{"fecha":"2014-05-01","cod":"9606301000","label":"De pl치stico o de tagua","sector":"游닍 Otros","fob":80.75179,"cif":0,"peso":10.42067},{"fecha":"2014-06-01","cod":"0303890090","label":"Desconocido","sector":"游붏 Pesca","fob":58.5435,"cif":0,"peso":53.91},{"fecha":"2014-06-01","cod":"0304590000","label":"Desconocido","sector":"游붏 Pesca","fob":0.03492,"cif":0,"peso":0.018},{"fecha":"2014-06-01","cod":"0306160000","label":"Camarones y langostinos y dem치s dec치podos natantia de agua fr칤a","sector":"游붏 Pesca","fob":1586.929,"cif":0,"peso":187.53},{"fecha":"2014-06-01","cod":"0306171100","label":"Enteros","sector":"游붏 Pesca","fob":2965.408,"cif":0,"peso":384.0},{"fecha":"2014-06-01","cod":"0306171300","label":"Colas con caparaz칩n, sin cocer en agua o vapor","sector":"游붏 Pesca","fob":542.378,"cif":0,"peso":60.52731},{"fecha":"2014-06-01","cod":"0306171900","label":"Desconocido","sector":"游붏 Pesca","fob":3883.1673,"cif":0,"peso":515.59279},{"fecha":"2014-06-01","cod":"0306179900","label":"Desconocido","sector":"游붏 Pesca","fob":24888.29719,"cif":0,"peso":3276.62064},{"fecha":"2014-06-01","cod":"0511912000","label":"Despojos de pescado, no comestibles","sector":"游닍 Otros","fob":19.431,"cif":0,"peso":13.0},{"fecha":"2014-06-01","cod":"0511919000","label":"Desconocido","sector":"游닍 Otros","fob":94.9,"cif":0,"peso":182.5},{"fecha":"2014-06-01","cod":"0603110000","label":"Rosas","sector":"游닍 Otros","fob":40.78553,"cif":0,"peso":5.3504},{"fecha":"2014-06-01","cod":"0603129000","label":"Desconocido","sector":"游닍 Otros","fob":0.45,"cif":0,"peso":0.054},{"fecha":"2014-06-01","cod":"0603199010","label":"Lirios","sector":"游닍 Otros","fob":0.00945,"cif":0,"peso":0.006},{"fecha":"2014-06-01","cod":"0603199090","label":"Desconocido","sector":"游닍 Otros","fob":0.51265,"cif":0,"peso":0.04755},{"fecha":"2014-06-01","cod":"0603900000","label":"Desconocido","sector":"游닍 Otros","fob":89.08264,"cif":0,"peso":1.89585},{"fecha":"2014-06-01","cod":"0803901100","label":"Tipo 춺cavendish valery췉","sector":"游꼛 Frutas","fob":7568.07715,"cif":0,"peso":17377.70118},{"fecha":"2014-06-01","cod":"0803901200","label":"Bocadillo","sector":"游꼛 Frutas","fob":29.3568,"cif":0,"peso":39.6},{"fecha":"2014-06-01","cod":"1211909000","label":"Desconocido","sector":"游닍 Otros","fob":53.14056,"cif":0,"peso":24.1548},{"fecha":"2014-06-01","cod":"1404909000","label":"Desconocido","sector":"游닍 Otros","fob":48.90609,"cif":0,"peso":38.0},{"fecha":"2014-06-01","cod":"1801001900","label":"Desconocido","sector":"游꼶 Cacao","fob":2465.523,"cif":0,"peso":850.425},{"fecha":"2014-06-01","cod":"2007999200","label":"Pur칠s y pastas","sector":"游닍 Otros","fob":49.1808,"cif":0,"peso":77.376},{"fecha":"2014-06-01","cod":"2009892000","label":"De maracuy치","sector":"游닍 Otros","fob":111.125,"cif":0,"peso":12.5},{"fecha":"2014-06-01","cod":"2301201100","label":"Con un contenido de grasa superior a 2% en peso","sector":"游닍 Otros","fob":2655.92155,"cif":0,"peso":1513.65},{"fecha":"2014-06-01","cod":"2603000000","label":"Minerales de cobre y sus concentrados.","sector":"游닍 Otros","fob":1496.63332,"cif":0,"peso":978.855},{"fecha":"2014-06-01","cod":"2616900000","label":":","sector":"游닍 Otros","fob":892.44837,"cif":0,"peso":1114.219},{"fecha":"2014-06-01","cod":"2616901000","label":"Minerales de oro y sus concentrados","sector":"游닍 Otros","fob":3440.53954,"cif":0,"peso":3017.537},{"fecha":"2014-06-01","cod":"3903190000","label":"Desconocido","sector":"游빖 Pl치sticos","fob":42.105,"cif":0,"peso":76.21},{"fecha":"2014-06-01","cod":"3915900000","label":"De los dem치s pl치sticos","sector":"游빖 Pl치sticos","fob":452.10415,"cif":0,"peso":803.5335},{"fecha":"2014-06-01","cod":"3921199000","label":"Desconocido","sector":"游빖 Pl치sticos","fob":8.6814,"cif":0,"peso":48.23},{"fecha":"2014-06-01","cod":"4102100000","label":"Con lana","sector":"游닍 Otros","fob":9.02,"cif":0,"peso":18.735},{"fecha":"2014-06-01","cod":"4104110000","label":"Plena flor sin dividir; divididos con la flor","sector":"游닍 Otros","fob":78.254,"cif":0,"peso":45.225},{"fecha":"2014-06-01","cod":"4403990000","label":"Desconocido","sector":"游뿻 Madera","fob":119.59765,"cif":0,"peso":1453.73},{"fecha":"2014-06-01","cod":"4407220000","label":"Virola, imbuia y balsa","sector":"游뿻 Madera","fob":2403.94408,"cif":0,"peso":707.48007},{"fecha":"2014-06-01","cod":"4407290000","label":"Desconocido","sector":"游뿻 Madera","fob":7.75725,"cif":0,"peso":2.014},{"fecha":"2014-06-01","cod":"4408900000","label":"Desconocido","sector":"游뿻 Madera","fob":40.81605,"cif":0,"peso":8.568},{"fecha":"2014-06-01","cod":"4820100000","label":"Libros registro, libros de contabilidad, talonarios , bloques memorandos, bloques de papel de cartas, agendas y art칤culos similares","sector":"游닍 Otros","fob":0.72,"cif":0,"peso":0.417},{"fecha":"2014-06-01","cod":"6504000000","label":"Sombreros y dem치s tocados, trenzados o fabricados por uni칩n de tiras de cualquier materia, incluso guarnecidos.","sector":"游닍 Otros","fob":1.3765,"cif":0,"peso":0.0048},{"fecha":"2014-06-01","cod":"7304900000","label":"Desconocido","sector":"游닍 Otros","fob":29.06,"cif":0,"peso":6.45},{"fecha":"2014-06-01","cod":"7403220000","label":"A base de cobreesta침o","sector":"游닍 Otros","fob":486.90423,"cif":0,"peso":113.37},{"fecha":"2014-06-01","cod":"7404000000","label":"Desperdicios y desechos, de cobre.","sector":"游닍 Otros","fob":2757.42751,"cif":0,"peso":686.021},{"fecha":"2014-06-01","cod":"7602000000","label":"Desperdicios y desechos, de aluminio.","sector":"游닍 Otros","fob":598.76577,"cif":0,"peso":444.09},{"fecha":"2014-06-01","cod":"8301409000","label":"Desconocido","sector":"游닍 Otros","fob":15.0,"cif":0,"peso":0.565},{"fecha":"2014-06-01","cod":"8431439000","label":"Desconocido","sector":"丘뙖잺 Maquinaria","fob":56.334,"cif":0,"peso":3.4},{"fecha":"2014-06-01","cod":"8479900000","label":"Partes","sector":"丘뙖잺 Maquinaria","fob":6.67552,"cif":0,"peso":0.062},{"fecha":"2014-06-01","cod":"8481100000","label":"V치lvulas reductoras de presi칩n","sector":"丘뙖잺 Maquinaria","fob":1.50697,"cif":0,"peso":0.006},{"fecha":"2014-06-01","cod":"8504409000","label":"Desconocido","sector":"游댋 El칠ctrico","fob":122.39674,"cif":0,"peso":1.5827},{"fecha":"2014-07-01","cod":"0303340000","label":"Rodaballos","sector":"游붏 Pesca","fob":177.21,"cif":0,"peso":81.0},{"fecha":"2014-07-01","cod":"0303690000","label":"Desconocido","sector":"游붏 Pesca","fob":46.6785,"cif":0,"peso":20.98},{"fecha":"2014-07-01","cod":"0303890090","label":"Desconocido","sector":"游붏 Pesca","fob":71.219,"cif":0,"peso":32.0},{"fecha":"2014-07-01","cod":"0304790090","label":"Desconocido","sector":"游붏 Pesca","fob":99.5236,"cif":0,"peso":54.0},{"fecha":"2014-07-01","cod":"0306160000","label":"Camarones y langostinos y dem치s dec치podos natantia de agua fr칤a","sector":"游붏 Pesca","fob":2722.7976,"cif":0,"peso":330.43496},{"fecha":"2014-07-01","cod":"0306171100","label":"Enteros","sector":"游붏 Pesca","fob":1356.056,"cif":0,"peso":192.0},{"fecha":"2014-07-01","cod":"0306171900","label":"Desconocido","sector":"游붏 Pesca","fob":2231.71161,"cif":0,"peso":283.88664},{"fecha":"2014-07-01","cod":"0306179100","label":"Camarones de r칤o de los g칠neros macrobrachium","sector":"游붏 Pesca","fob":766.1555,"cif":0,"peso":87.79371},{"fecha":"2014-07-01","cod":"0306179900","label":"Desconocido","sector":"游붏 Pesca","fob":10704.18702,"cif":0,"peso":1355.49432},{"fecha":"2014-07-01","cod":"0603110000","label":"Rosas","sector":"游닍 Otros","fob":181.66774,"cif":0,"peso":30.46901},{"fecha":"2014-07-01","cod":"0603199090","label":"Desconocido","sector":"游닍 Otros","fob":0.695,"cif":0,"peso":0.0833},{"fecha":"2014-07-01","cod":"0603900000","label":"Desconocido","sector":"游닍 Otros","fob":72.9764,"cif":0,"peso":1.5971},{"fecha":"2014-07-01","cod":"0803901100","label":"Tipo 춺cavendish valery췉","sector":"游꼛 Frutas","fob":11341.70315,"cif":0,"peso":26147.51764},{"fecha":"2014-07-01","cod":"0803901200","label":"Bocadillo","sector":"游꼛 Frutas","fob":58.70248,"cif":0,"peso":79.185},{"fecha":"2014-07-01","cod":"0811909900","label":"Desconocido","sector":"游꼛 Frutas","fob":20.515,"cif":0,"peso":24.0},{"fecha":"2014-07-01","cod":"1211909000","label":"Desconocido","sector":"游닍 Otros","fob":53.66086,"cif":0,"peso":24.3913},{"fecha":"2014-07-01","cod":"1404909000","label":"Desconocido","sector":"游닍 Otros","fob":23.963,"cif":0,"peso":20.2},{"fecha":"2014-07-01","cod":"2301201100","label":"Con un contenido de grasa superior a 2% en peso","sector":"游닍 Otros","fob":2884.24986,"cif":0,"peso":1644.775},{"fecha":"2014-07-01","cod":"2603000000","label":"Minerales de cobre y sus concentrados.","sector":"游닍 Otros","fob":1046.60245,"cif":0,"peso":626.744},{"fecha":"2014-07-01","cod":"2616900000","label":":","sector":"游닍 Otros","fob":393.56536,"cif":0,"peso":670.61},{"fecha":"2014-07-01","cod":"2616901000","label":"Minerales de oro y sus concentrados","sector":"游닍 Otros","fob":2489.11896,"cif":0,"peso":2223.875},{"fecha":"2014-07-01","cod":"3902100000","label":"Polipropileno","sector":"游빖 Pl치sticos","fob":0.25,"cif":0,"peso":0.35},{"fecha":"2014-07-01","cod":"3902300000","label":"Copol칤meros de propileno","sector":"游빖 Pl치sticos","fob":0.25,"cif":0,"peso":0.15},{"fecha":"2014-07-01","cod":"3915900000","label":"De los dem치s pl치sticos","sector":"游빖 Pl치sticos","fob":523.95491,"cif":0,"peso":955.029},{"fecha":"2014-07-01","cod":"3921199000","label":"Desconocido","sector":"游빖 Pl치sticos","fob":7.73235,"cif":0,"peso":51.549},{"fecha":"2014-07-01","cod":"4102100000","label":"Con lana","sector":"游닍 Otros","fob":32.01,"cif":0,"peso":50.94},{"fecha":"2014-07-01","cod":"4403990000","label":"Desconocido","sector":"游뿻 Madera","fob":79.3208,"cif":0,"peso":1402.04},{"fecha":"2014-07-01","cod":"4407220000","label":"Virola, imbuia y balsa","sector":"游뿻 Madera","fob":2244.66375,"cif":0,"peso":687.56636},{"fecha":"2014-07-01","cod":"4407290000","label":"Desconocido","sector":"游뿻 Madera","fob":8.8,"cif":0,"peso":22.45},{"fecha":"2014-07-01","cod":"4408900000","label":"Desconocido","sector":"游뿻 Madera","fob":53.68045,"cif":0,"peso":9.18},{"fecha":"2014-07-01","cod":"4707300000","label":"Papel o cart칩n obtenido principalmente a partir de pasta mec치nica","sector":"游닍 Otros","fob":30.05506,"cif":0,"peso":214.679},{"fecha":"2014-07-01","cod":"6505002000","label":"Sombreros y dem치s tocados de fieltro, fabricados con cascos o platos de la partida 65.01, incluso guarnecidos","sector":"游닍 Otros","fob":3.4105,"cif":0,"peso":0.014},{"fecha":"2014-07-01","cod":"7318240000","label":"Pasadores, clavijas y chavetas","sector":"游닍 Otros","fob":0.00945,"cif":0,"peso":0.02},{"fecha":"2014-07-01","cod":"7403220000","label":"A base de cobreesta침o","sector":"游닍 Otros","fob":204.5726,"cif":0,"peso":46.846},{"fecha":"2014-07-01","cod":"7404000000","label":"Desperdicios y desechos, de cobre.","sector":"游닍 Otros","fob":2297.54239,"cif":0,"peso":431.278},{"fecha":"2014-07-01","cod":"7602000000","label":"Desperdicios y desechos, de aluminio.","sector":"游닍 Otros","fob":126.50558,"cif":0,"peso":105.413},{"fecha":"2014-07-01","cod":"8412900000","label":"Partes","sector":"丘뙖잺 Maquinaria","fob":13.57338,"cif":0,"peso":0.101},{"fecha":"2014-07-01","cod":"8431439000","label":"Desconocido","sector":"丘뙖잺 Maquinaria","fob":1.23846,"cif":0,"peso":0.04},{"fecha":"2014-07-01","cod":"8465919900","label":"Desconocido","sector":"丘뙖잺 Maquinaria","fob":26.0,"cif":0,"peso":4.5},{"fecha":"2014-07-01","cod":"9606301000","label":"De pl치stico o de tagua","sector":"游닍 Otros","fob":402.74273,"cif":0,"peso":38.30405},{"fecha":"2014-08-01","cod":"0303340000","label":"Rodaballos","sector":"游붏 Pesca","fob":99.262,"cif":0,"peso":54.0},{"fecha":"2014-08-01","cod":"0303390000","label":"Desconocido","sector":"游붏 Pesca","fob":187.896,"cif":0,"peso":108.0},{"fecha":"2014-08-01","cod":"0303690000","label":"Desconocido","sector":"游붏 Pesca","fob":66.445,"cif":0,"peso":27.0},{"fecha":"2014-08-01","cod":"0303890090","label":"Desconocido","sector":"游붏 Pesca","fob":246.55395,"cif":0,"peso":130.52},{"fecha":"2014-08-01","cod":"0304990090","label":"Desconocido","sector":"游붏 Pesca","fob":10.9175,"cif":0,"peso":19.85},{"fecha":"2014-08-01","cod":"0306160000","label":"Camarones y langostinos y dem치s dec치podos natantia de agua fr칤a","sector":"游붏 Pesca","fob":3249.4709,"cif":0,"peso":398.66095},{"fecha":"2014-08-01","cod":"0306171100","label":"Enteros","sector":"游붏 Pesca","fob":411.44,"cif":0,"peso":48.0},{"fecha":"2014-08-01","cod":"0306171300","label":"Colas con caparaz칩n, sin cocer en agua o vapor","sector":"游붏 Pesca","fob":553.02,"cif":0,"peso":59.87415},{"fecha":"2014-08-01","cod":"0306171900","label":"Desconocido","sector":"游붏 Pesca","fob":1631.6733,"cif":0,"peso":190.44266},{"fecha":"2014-08-01","cod":"0306179100","label":"Camarones de r칤o de los g칠neros macrobrachium","sector":"游붏 Pesca","fob":754.349,"cif":0,"peso":87.7438},{"fecha":"2014-08-01","cod":"0306179900","label":"Desconocido","sector":"游붏 Pesca","fob":9161.65628,"cif":0,"peso":1105.85114},{"fecha":"2014-08-01","cod":"0511912000","label":"Despojos de pescado, no comestibles","sector":"游닍 Otros","fob":38.862,"cif":0,"peso":26.0},{"fecha":"2014-08-01","cod":"0603110000","label":"Rosas","sector":"游닍 Otros","fob":29.73623,"cif":0,"peso":5.50533},{"fecha":"2014-08-01","cod":"0603129000","label":"Desconocido","sector":"游닍 Otros","fob":0.15678,"cif":0,"peso":0.0405},{"fecha":"2014-08-01","cod":"0603900000","label":"Desconocido","sector":"游닍 Otros","fob":48.60375,"cif":0,"peso":1.4025},{"fecha":"2014-08-01","cod":"0803901100","label":"Tipo 춺cavendish valery췉","sector":"游꼛 Frutas","fob":16334.2048,"cif":0,"peso":36919.32951},{"fecha":"2014-08-01","cod":"0803901200","label":"Bocadillo","sector":"游꼛 Frutas","fob":157.9826,"cif":0,"peso":166.917},{"fecha":"2014-08-01","cod":"1211909000","label":"Desconocido","sector":"游닍 Otros","fob":55.35442,"cif":0,"peso":25.1611},{"fecha":"2014-08-01","cod":"1801001900","label":"Desconocido","sector":"游꼶 Cacao","fob":937.5,"cif":0,"peso":300.0},{"fecha":"2014-08-01","cod":"1803100000","label":"Sin desgrasar","sector":"游꼶 Cacao","fob":64.4,"cif":0,"peso":20.0},{"fecha":"2014-08-01","cod":"2007999200","label":"Pur칠s y pastas","sector":"游닍 Otros","fob":8.0,"cif":0,"peso":20.0},{"fecha":"2014-08-01","cod":"2301201100","label":"Con un contenido de grasa superior a 2% en peso","sector":"游닍 Otros","fob":5326.98971,"cif":0,"peso":2945.585},{"fecha":"2014-08-01","cod":"2603000000","label":"Minerales de cobre y sus concentrados.","sector":"游닍 Otros","fob":934.52264,"cif":0,"peso":555.197},{"fecha":"2014-08-01","cod":"2616901000","label":"Minerales de oro y sus concentrados","sector":"游닍 Otros","fob":3197.57512,"cif":0,"peso":3065.88},{"fecha":"2014-08-01","cod":"3915100000","label":"De pol칤meros de etileno","sector":"游빖 Pl치sticos","fob":7.50512,"cif":0,"peso":19.035},{"fecha":"2014-08-01","cod":"3915900000","label":"De los dem치s pl치sticos","sector":"游빖 Pl치sticos","fob":200.30769,"cif":0,"peso":398.422},{"fecha":"2014-08-01","cod":"3915900090","label":"Desconocido","sector":"游빖 Pl치sticos","fob":19.09841,"cif":0,"peso":39.343},{"fecha":"2014-08-01","cod":"4104190000","label":"Desconocido","sector":"游닍 Otros","fob":19.56728,"cif":0,"peso":19.2565},{"fecha":"2014-08-01","cod":"4403990000","label":"Desconocido","sector":"游뿻 Madera","fob":138.22,"cif":0,"peso":2220.4},{"fecha":"2014-08-01","cod":"4407220000","label":"Virola, imbuia y balsa","sector":"游뿻 Madera","fob":2875.39239,"cif":0,"peso":844.80539},{"fecha":"2014-08-01","cod":"4408900000","label":"Desconocido","sector":"游뿻 Madera","fob":35.2275,"cif":0,"peso":8.568},{"fecha":"2014-08-01","cod":"5305001100","label":"En bruto","sector":"游닍 Otros","fob":22.5,"cif":0,"peso":11.25},{"fecha":"2014-08-01","cod":"6502001000","label":"De paja toquilla o de paja mocora","sector":"游닍 Otros","fob":14.0,"cif":0,"peso":0.097},{"fecha":"2014-08-01","cod":"7009100000","label":"Espejos retrovisores para veh칤culos","sector":"游닍 Otros","fob":0.328,"cif":0,"peso":0.0125},{"fecha":"2014-08-01","cod":"7403220000","label":"A base de cobreesta침o","sector":"游닍 Otros","fob":88.2756,"cif":0,"peso":21.018},{"fecha":"2014-08-01","cod":"7404000000","label":"Desperdicios y desechos, de cobre.","sector":"游닍 Otros","fob":3007.22968,"cif":0,"peso":537.824},{"fecha":"2014-08-01","cod":"7602000000","label":"Desperdicios y desechos, de aluminio.","sector":"游닍 Otros","fob":160.47605,"cif":0,"peso":150.936},{"fecha":"2014-08-01","cod":"8301401000","label":"Para cajas de caudales","sector":"游닍 Otros","fob":51.0,"cif":0,"peso":1.01},{"fecha":"2014-08-01","cod":"8301409000","label":"Desconocido","sector":"游닍 Otros","fob":18.9,"cif":0,"peso":0.81},{"fecha":"2014-08-01","cod":"8412290000","label":"Desconocido","sector":"丘뙖잺 Maquinaria","fob":25.52,"cif":0,"peso":1.9},{"fecha":"2014-08-01","cod":"8512201000","label":"Faros de carretera","sector":"游댋 El칠ctrico","fob":0.29,"cif":0,"peso":0.0375},{"fecha":"2014-08-01","cod":"9606301000","label":"De pl치stico o de tagua","sector":"游닍 Otros","fob":66.61221,"cif":0,"peso":6.34402},{"fecha":"2014-09-01","cod":"0303340000","label":"Rodaballos","sector":"游붏 Pesca","fob":13.91584,"cif":0,"peso":9.01},{"fecha":"2014-09-01","cod":"0303390000","label":"Desconocido","sector":"游붏 Pesca","fob":518.09056,"cif":0,"peso":257.99},{"fecha":"2014-09-01","cod":"0303890090","label":"Desconocido","sector":"游붏 Pesca","fob":165.81152,"cif":0,"peso":80.5},{"fecha":"2014-09-01","cod":"0306160000","label":"Camarones y langostinos y dem치s dec치podos natantia de agua fr칤a","sector":"游붏 Pesca","fob":1027.394,"cif":0,"peso":117.256},{"fecha":"2014-09-01","cod":"0306171300","label":"Colas con caparaz칩n, sin cocer en agua o vapor","sector":"游붏 Pesca","fob":589.184,"cif":0,"peso":63.73876},{"fecha":"2014-09-01","cod":"0306171900","label":"Desconocido","sector":"游붏 Pesca","fob":812.5117,"cif":0,"peso":91.988},{"fecha":"2014-09-01","cod":"0306179100","label":"Camarones de r칤o de los g칠neros macrobrachium","sector":"游붏 Pesca","fob":176.7704,"cif":0,"peso":22.06296},{"fecha":"2014-09-01","cod":"0306179900","label":"Desconocido","sector":"游붏 Pesca","fob":10289.2692,"cif":0,"peso":1183.15129},{"fecha":"2014-09-01","cod":"0603110000","label":"Rosas","sector":"游닍 Otros","fob":26.65238,"cif":0,"peso":5.0023},{"fecha":"2014-09-01","cod":"0603129000","label":"Desconocido","sector":"游닍 Otros","fob":0.01003,"cif":0,"peso":0.0045},{"fecha":"2014-09-01","cod":"0603900000","label":"Desconocido","sector":"游닍 Otros","fob":66.9874,"cif":0,"peso":1.2477},{"fecha":"2014-09-01","cod":"0803901100","label":"Tipo 춺cavendish valery췉","sector":"游꼛 Frutas","fob":14646.07315,"cif":0,"peso":30971.42855},{"fecha":"2014-09-01","cod":"0803901200","label":"Bocadillo","sector":"游꼛 Frutas","fob":397.36782,"cif":0,"peso":446.7238},{"fecha":"2014-09-01","cod":"0811909900","label":"Desconocido","sector":"游꼛 Frutas","fob":20.265,"cif":0,"peso":24.0},{"fecha":"2014-09-01","cod":"1404909000","label":"Desconocido","sector":"游닍 Otros","fob":9.55,"cif":0,"peso":33.68},{"fecha":"2014-09-01","cod":"1801001900","label":"Desconocido","sector":"游꼶 Cacao","fob":973.5,"cif":0,"peso":300.0},{"fecha":"2014-09-01","cod":"2007999200","label":"Pur칠s y pastas","sector":"游닍 Otros","fob":10.9956,"cif":0,"peso":19.992},{"fecha":"2014-09-01","cod":"2008910000","label":"Palmitos","sector":"游닍 Otros","fob":57.43589,"cif":0,"peso":20.83553},{"fecha":"2014-09-01","cod":"2301201100","label":"Con un contenido de grasa superior a 2% en peso","sector":"游닍 Otros","fob":1678.66802,"cif":0,"peso":938.83},{"fecha":"2014-09-01","cod":"2301201900","label":"Con un contenido de grasa inferior o igual a 2% en peso","sector":"游닍 Otros","fob":36.96,"cif":0,"peso":21.28},{"fecha":"2014-09-01","cod":"2603000000","label":"Minerales de cobre y sus concentrados.","sector":"游닍 Otros","fob":2326.75848,"cif":0,"peso":1469.28},{"fecha":"2014-09-01","cod":"2616901000","label":"Minerales de oro y sus concentrados","sector":"游닍 Otros","fob":4014.28012,"cif":0,"peso":3736.419},{"fecha":"2014-09-01","cod":"2617100000","label":"Minerales de antimonio y sus concentrados","sector":"游닍 Otros","fob":16.36145,"cif":0,"peso":23.374},{"fecha":"2014-09-01","cod":"2709000000","label":"Aceites crudos de petr칩leo o de mineral bituminoso.","sector":"游닍 Otros","fob":29976.97514,"cif":0,"peso":50929.97902},{"fecha":"2014-09-01","cod":"2941109000","label":"Desconocido","sector":"游빍 Qu칤micos","fob":9.6192,"cif":0,"peso":0.234},{"fecha":"2014-09-01","cod":"2941909000","label":"Desconocido","sector":"游빍 Qu칤micos","fob":276.0,"cif":0,"peso":0.054},{"fecha":"2014-09-01","cod":"3902100000","label":"Polipropileno","sector":"游빖 Pl치sticos","fob":0.509,"cif":0,"peso":0.509},{"fecha":"2014-09-01","cod":"3915100000","label":"De pol칤meros de etileno","sector":"游빖 Pl치sticos","fob":418.77095,"cif":0,"peso":683.835},{"fecha":"2014-09-01","cod":"3915900000","label":"De los dem치s pl치sticos","sector":"游빖 Pl치sticos","fob":83.41131,"cif":0,"peso":139.433},{"fecha":"2014-09-01","cod":"3915900010","label":"Botellas de poli","sector":"游빖 Pl치sticos","fob":75.25939,"cif":0,"peso":113.172},{"fecha":"2014-09-01","cod":"3915900090","label":"Desconocido","sector":"游빖 Pl치sticos","fob":177.15285,"cif":0,"peso":421.832},{"fecha":"2014-09-01","cod":"3921199000","label":"Desconocido","sector":"游빖 Pl치sticos","fob":22.545,"cif":0,"peso":125.25},{"fecha":"2014-09-01","cod":"4102100000","label":"Con lana","sector":"游닍 Otros","fob":31.68,"cif":0,"peso":52.2},{"fecha":"2014-09-01","cod":"4403990000","label":"Desconocido","sector":"游뿻 Madera","fob":229.76592,"cif":0,"peso":3422.308},{"fecha":"2014-09-01","cod":"4407220000","label":"Virola, imbuia y balsa","sector":"游뿻 Madera","fob":3206.62466,"cif":0,"peso":975.77199},{"fecha":"2014-09-01","cod":"4408900000","label":"Desconocido","sector":"游뿻 Madera","fob":70.455,"cif":0,"peso":18.3456},{"fecha":"2014-09-01","cod":"4413000000","label":"Madera densificada en bloques, tablas, tiras o perfiles.","sector":"游뿻 Madera","fob":125.78026,"cif":0,"peso":51.3784},{"fecha":"2014-09-01","cod":"5305001100","label":"En bruto","sector":"游닍 Otros","fob":45.48125,"cif":0,"peso":23.75},{"fecha":"2014-09-01","cod":"6504000000","label":"Sombreros y dem치s tocados, trenzados o fabricados por uni칩n de tiras de cualquier materia, incluso guarnecidos.","sector":"游닍 Otros","fob":0.399,"cif":0,"peso":0.00245},{"fecha":"2014-09-01","cod":"7404000000","label":"Desperdicios y desechos, de cobre.","sector":"游닍 Otros","fob":3344.06445,"cif":0,"peso":640.2925},{"fecha":"2014-09-01","cod":"7602000000","label":"Desperdicios y desechos, de aluminio.","sector":"游닍 Otros","fob":345.84916,"cif":0,"peso":229.8795},{"fecha":"2014-09-01","cod":"8301401000","label":"Para cajas de caudales","sector":"游닍 Otros","fob":187.0,"cif":0,"peso":3.398},{"fecha":"2014-09-01","cod":"8301409000","label":"Desconocido","sector":"游닍 Otros","fob":63.0,"cif":0,"peso":3.381},{"fecha":"2014-09-01","cod":"8483109900","label":"Desconocido","sector":"丘뙖잺 Maquinaria","fob":7.344,"cif":0,"peso":1.38},{"fecha":"2014-09-01","cod":"8544609000","label":"Desconocido","sector":"游댋 El칠ctrico","fob":547.81296,"cif":0,"peso":57.971},{"fecha":"2014-09-01","cod":"9606301000","label":"De pl치stico o de tagua","sector":"游닍 Otros","fob":326.92646,"cif":0,"peso":30.591},{"fecha":"2014-09-01","cod":"9606309000","label":"Desconocido","sector":"游닍 Otros","fob":20.23,"cif":0,"peso":17.0},{"fecha":"2014-10-01","cod":"0303340000","label":"Rodaballos","sector":"游붏 Pesca","fob":199.9372,"cif":0,"peso":106.0},{"fecha":"2014-10-01","cod":"0303390000","label":"Desconocido","sector":"游붏 Pesca","fob":1.339,"cif":0,"peso":0.05},{"fecha":"2014-10-01","cod":"0303430000","label":"Listados o bonitos de vientre rayado","sector":"游붏 Pesca","fob":0.00174,"cif":0,"peso":0.00174},{"fecha":"2014-10-01","cod":"0303530000","label":"Sardinas , sardinelas  y espadines","sector":"游붏 Pesca","fob":0.00258,"cif":0,"peso":0.00258},{"fecha":"2014-10-01","cod":"0303540000","label":"Caballas","sector":"游붏 Pesca","fob":0.0026,"cif":0,"peso":0.0026},{"fecha":"2014-10-01","cod":"0303660000","label":"Merluzas","sector":"游붏 Pesca","fob":0.00566,"cif":0,"peso":0.00566},{"fecha":"2014-10-01","cod":"0303890010","label":"Dorado","sector":"游붏 Pesca","fob":0.00383,"cif":0,"peso":0.00383},{"fecha":"2014-10-01","cod":"0303890090","label":"Desconocido","sector":"游붏 Pesca","fob":58.53684,"cif":0,"peso":27.03684},{"fecha":"2014-10-01","cod":"0304740000","label":"Merluzas","sector":"游붏 Pesca","fob":0.00071,"cif":0,"peso":0.00071},{"fecha":"2014-10-01","cod":"0304990090","label":"Desconocido","sector":"游붏 Pesca","fob":0.0002,"cif":0,"peso":0.0002},{"fecha":"2014-10-01","cod":"0306160000","label":"Camarones y langostinos y dem치s dec치podos natantia de agua fr칤a","sector":"游붏 Pesca","fob":886.0775,"cif":0,"peso":95.256},{"fecha":"2014-10-01","cod":"0306171300","label":"Colas con caparaz칩n, sin cocer en agua o vapor","sector":"游붏 Pesca","fob":593.776,"cif":0,"peso":64.64593},{"fecha":"2014-10-01","cod":"0306171900","label":"Desconocido","sector":"游붏 Pesca","fob":756.47644,"cif":0,"peso":89.097},{"fecha":"2014-10-01","cod":"0306179100","label":"Camarones de r칤o de los g칠neros macrobrachium","sector":"游붏 Pesca","fob":187.2,"cif":0,"peso":22.64356},{"fecha":"2014-10-01","cod":"0306179900","label":"Desconocido","sector":"游붏 Pesca","fob":1534.32859,"cif":0,"peso":174.78532},{"fecha":"2014-10-01","cod":"0511912000","label":"Despojos de pescado, no comestibles","sector":"游닍 Otros","fob":18.59,"cif":0,"peso":13.0},{"fecha":"2014-10-01","cod":"0603110000","label":"Rosas","sector":"游닍 Otros","fob":70.75495,"cif":0,"peso":12.89768},{"fecha":"2014-10-01","cod":"0603129000","label":"Desconocido","sector":"游닍 Otros","fob":0.16275,"cif":0,"peso":0.0405},{"fecha":"2014-10-01","cod":"0603900000","label":"Desconocido","sector":"游닍 Otros","fob":95.21955,"cif":0,"peso":1.53315},{"fecha":"2014-10-01","cod":"0803901100","label":"Tipo 춺cavendish valery췉","sector":"游꼛 Frutas","fob":10059.17736,"cif":0,"peso":22321.23391},{"fecha":"2014-10-01","cod":"0803901200","label":"Bocadillo","sector":"游꼛 Frutas","fob":274.83806,"cif":0,"peso":338.0126},{"fecha":"2014-10-01","cod":"0811909900","label":"Desconocido","sector":"游꼛 Frutas","fob":20.515,"cif":0,"peso":24.0},{"fecha":"2014-10-01","cod":"1211909000","label":"Desconocido","sector":"游닍 Otros","fob":102.97496,"cif":0,"peso":46.8068},{"fecha":"2014-10-01","cod":"1404909000","label":"Desconocido","sector":"游닍 Otros","fob":3.465,"cif":0,"peso":18.23},{"fecha":"2014-10-01","cod":"1604141000","label":"Atunes","sector":"游볾 Conservas","fob":0.2163,"cif":0,"peso":0.0284},{"fecha":"2014-10-01","cod":"1605540000","label":"Jibias, globitos, calamares y potas","sector":"游볾 Conservas","fob":0.0021,"cif":0,"peso":0.0021},{"fecha":"2014-10-01","cod":"1803100000","label":"Sin desgrasar","sector":"游꼶 Cacao","fob":19.04376,"cif":0,"peso":6.0},{"fecha":"2014-10-01","cod":"2008910000","label":"Palmitos","sector":"游닍 Otros","fob":28.34495,"cif":0,"peso":9.92697},{"fecha":"2014-10-01","cod":"2301201100","label":"Con un contenido de grasa superior a 2% en peso","sector":"游닍 Otros","fob":2505.07336,"cif":0,"peso":1450.181},{"fecha":"2014-10-01","cod":"2505900000","label":"Desconocido","sector":"游닍 Otros","fob":1.1,"cif":0,"peso":22.0},{"fecha":"2014-10-01","cod":"2603000000","label":"Minerales de cobre y sus concentrados.","sector":"游닍 Otros","fob":1573.85835,"cif":0,"peso":921.58417},{"fecha":"2014-10-01","cod":"2616901000","label":"Minerales de oro y sus concentrados","sector":"游닍 Otros","fob":2620.58022,"cif":0,"peso":2674.706},{"fecha":"2014-10-01","cod":"3903190000","label":"Desconocido","sector":"游빖 Pl치sticos","fob":41.917,"cif":0,"peso":76.12},{"fecha":"2014-10-01","cod":"3915100000","label":"De pol칤meros de etileno","sector":"游빖 Pl치sticos","fob":213.51179,"cif":0,"peso":323.473},{"fecha":"2014-10-01","cod":"3915900090","label":"Desconocido","sector":"游빖 Pl치sticos","fob":91.88136,"cif":0,"peso":222.269},{"fecha":"2014-10-01","cod":"4403990000","label":"Desconocido","sector":"游뿻 Madera","fob":46.4946,"cif":0,"peso":810.58},{"fecha":"2014-10-01","cod":"4407220000","label":"Virola, imbuia y balsa","sector":"游뿻 Madera","fob":2856.43202,"cif":0,"peso":875.294368},{"fecha":"2014-10-01","cod":"4407990000","label":"Desconocido","sector":"游뿻 Madera","fob":13.3,"cif":0,"peso":49.45},{"fecha":"2014-10-01","cod":"4408900000","label":"Desconocido","sector":"游뿻 Madera","fob":73.396,"cif":0,"peso":18.567},{"fecha":"2014-10-01","cod":"4413000000","label":"Madera densificada en bloques, tablas, tiras o perfiles.","sector":"游뿻 Madera","fob":151.82092,"cif":0,"peso":62.12796},{"fecha":"2014-10-01","cod":"4421909000","label":"Desconocido","sector":"游뿻 Madera","fob":61.32672,"cif":0,"peso":19.584},{"fecha":"2014-10-01","cod":"4818300000","label":"Manteles y servilletas","sector":"游닍 Otros","fob":0.1725,"cif":0,"peso":0.09},{"fecha":"2014-10-01","cod":"7326909000","label":"Desconocido","sector":"游닍 Otros","fob":0.90422,"cif":0,"peso":0.045},{"fecha":"2014-10-01","cod":"7404000000","label":"Desperdicios y desechos, de cobre.","sector":"游닍 Otros","fob":2798.4906,"cif":0,"peso":530.555},{"fecha":"2014-10-01","cod":"7602000000","label":"Desperdicios y desechos, de aluminio.","sector":"游닍 Otros","fob":72.73905,"cif":0,"peso":46.181},{"fecha":"2014-10-01","cod":"8483909000","label":"Partes","sector":"丘뙖잺 Maquinaria","fob":2.352,"cif":0,"peso":0.333},{"fecha":"2014-10-01","cod":"9606301000","label":"De pl치stico o de tagua","sector":"游닍 Otros","fob":92.90535,"cif":0,"peso":10.15471},{"fecha":"2014-11-01","cod":"0306160000","label":"Camarones y langostinos y dem치s dec치podos natantia de agua fr칤a","sector":"游붏 Pesca","fob":407.25,"cif":0,"peso":47.99},{"fecha":"2014-11-01","cod":"0306179900","label":"Desconocido","sector":"游붏 Pesca","fob":1543.85105,"cif":0,"peso":185.288},{"fecha":"2014-11-01","cod":"0511912000","label":"Despojos de pescado, no comestibles","sector":"游닍 Otros","fob":18.59,"cif":0,"peso":13.0},{"fecha":"2014-11-01","cod":"0603110000","label":"Rosas","sector":"游닍 Otros","fob":94.25221,"cif":0,"peso":7.36809},{"fecha":"2014-11-01","cod":"0603199090","label":"Desconocido","sector":"游닍 Otros","fob":0.9062,"cif":0,"peso":0.19245},{"fecha":"2014-11-01","cod":"0603900000","label":"Desconocido","sector":"游닍 Otros","fob":30.066,"cif":0,"peso":0.81175},{"fecha":"2014-11-01","cod":"0803901100","label":"Tipo 춺cavendish valery췉","sector":"游꼛 Frutas","fob":10124.49512,"cif":0,"peso":22562.883158},{"fecha":"2014-11-01","cod":"0803901200","label":"Bocadillo","sector":"游꼛 Frutas","fob":190.25004,"cif":0,"peso":265.0161},{"fecha":"2014-11-01","cod":"0811909900","label":"Desconocido","sector":"游꼛 Frutas","fob":40.53,"cif":0,"peso":48.0},{"fecha":"2014-11-01","cod":"0901212000","label":"Molido","sector":"游닍 Otros","fob":4.8222,"cif":0,"peso":0.432},{"fecha":"2014-11-01","cod":"1211909000","label":"Desconocido","sector":"游닍 Otros","fob":48.56434,"cif":0,"peso":22.0747},{"fecha":"2014-11-01","cod":"1404909000","label":"Desconocido","sector":"游닍 Otros","fob":48.0,"cif":0,"peso":36.0},{"fecha":"2014-11-01","cod":"1801001900","label":"Desconocido","sector":"游꼶 Cacao","fob":763.77956,"cif":0,"peso":250.125},{"fecha":"2014-11-01","cod":"2007999200","label":"Pur칠s y pastas","sector":"游닍 Otros","fob":8.0,"cif":0,"peso":20.0},{"fecha":"2014-11-01","cod":"2101110000","label":"Extractos, esencias y concentrados","sector":"游닍 Otros","fob":1.4625,"cif":0,"peso":0.0765},{"fecha":"2014-11-01","cod":"2301201100","label":"Con un contenido de grasa superior a 2% en peso","sector":"游닍 Otros","fob":4731.8951,"cif":0,"peso":2621.307},{"fecha":"2014-11-01","cod":"2603000000","label":"Minerales de cobre y sus concentrados.","sector":"游닍 Otros","fob":2486.20461,"cif":0,"peso":1319.73838},{"fecha":"2014-11-01","cod":"2616901000","label":"Minerales de oro y sus concentrados","sector":"游닍 Otros","fob":2975.16236,"cif":0,"peso":2973.57},{"fecha":"2014-11-01","cod":"2709000000","label":"Aceites crudos de petr칩leo o de mineral bituminoso.","sector":"游닍 Otros","fob":27810.0812,"cif":0,"peso":76923.07692},{"fecha":"2014-11-01","cod":"3915900090","label":"Desconocido","sector":"游빖 Pl치sticos","fob":81.29593,"cif":0,"peso":198.646},{"fecha":"2014-11-01","cod":"3921199000","label":"Desconocido","sector":"游빖 Pl치sticos","fob":11.217,"cif":0,"peso":74.78},{"fecha":"2014-11-01","cod":"4102100000","label":"Con lana","sector":"游닍 Otros","fob":10.956,"cif":0,"peso":14.9},{"fecha":"2014-11-01","cod":"4403990000","label":"Desconocido","sector":"游뿻 Madera","fob":142.31406,"cif":0,"peso":1608.222},{"fecha":"2014-11-01","cod":"4407220000","label":"Virola, imbuia y balsa","sector":"游뿻 Madera","fob":4083.70557,"cif":0,"peso":1258.35706},{"fecha":"2014-11-01","cod":"4408900000","label":"Desconocido","sector":"游뿻 Madera","fob":152.1995,"cif":0,"peso":37.6704},{"fecha":"2014-11-01","cod":"4413000000","label":"Madera densificada en bloques, tablas, tiras o perfiles.","sector":"游뿻 Madera","fob":219.84705,"cif":0,"peso":337.1884},{"fecha":"2014-11-01","cod":"6502001000","label":"De paja toquilla o de paja mocora","sector":"游닍 Otros","fob":12.56,"cif":0,"peso":0.059},{"fecha":"2014-11-01","cod":"6504000000","label":"Sombreros y dem치s tocados, trenzados o fabricados por uni칩n de tiras de cualquier materia, incluso guarnecidos.","sector":"游닍 Otros","fob":9.1713,"cif":0,"peso":0.03425},{"fecha":"2014-11-01","cod":"7404000000","label":"Desperdicios y desechos, de cobre.","sector":"游닍 Otros","fob":3035.75264,"cif":0,"peso":657.089},{"fecha":"2014-11-01","cod":"7602000000","label":"Desperdicios y desechos, de aluminio.","sector":"游닍 Otros","fob":206.3609,"cif":0,"peso":200.0},{"fecha":"2014-11-01","cod":"8301401000","label":"Para cajas de caudales","sector":"游닍 Otros","fob":41.5,"cif":0,"peso":0.52756},{"fecha":"2014-11-01","cod":"8301409000","label":"Desconocido","sector":"游닍 Otros","fob":32.65,"cif":0,"peso":1.31885},{"fecha":"2014-11-01","cod":"8431439000","label":"Desconocido","sector":"丘뙖잺 Maquinaria","fob":11.43941,"cif":0,"peso":0.046},{"fecha":"2014-11-01","cod":"9606301000","label":"De pl치stico o de tagua","sector":"游닍 Otros","fob":124.85494,"cif":0,"peso":10.4},{"fecha":"2014-12-01","cod":"0303390000","label":"Desconocido","sector":"游붏 Pesca","fob":50.549,"cif":0,"peso":27.0},{"fecha":"2014-12-01","cod":"0303890090","label":"Desconocido","sector":"游붏 Pesca","fob":88.6845,"cif":0,"peso":53.5},{"fecha":"2014-12-01","cod":"0306160000","label":"Camarones y langostinos y dem치s dec치podos natantia de agua fr칤a","sector":"游붏 Pesca","fob":296.04,"cif":0,"peso":46.68},{"fecha":"2014-12-01","cod":"0306171900","label":"Desconocido","sector":"游붏 Pesca","fob":252.5438,"cif":0,"peso":39.092},{"fecha":"2014-12-01","cod":"0306179900","label":"Desconocido","sector":"游붏 Pesca","fob":3556.95588,"cif":0,"peso":423.65906},{"fecha":"2014-12-01","cod":"0511912000","label":"Despojos de pescado, no comestibles","sector":"游닍 Otros","fob":18.59,"cif":0,"peso":13.0},{"fecha":"2014-12-01","cod":"0511919000","label":"Desconocido","sector":"游닍 Otros","fob":25.5,"cif":0,"peso":51.0},{"fecha":"2014-12-01","cod":"0603110000","label":"Rosas","sector":"游닍 Otros","fob":125.6166,"cif":0,"peso":11.91086},{"fecha":"2014-12-01","cod":"0603199090","label":"Desconocido","sector":"游닍 Otros","fob":1.3022,"cif":0,"peso":0.2216},{"fecha":"2014-12-01","cod":"0603900000","label":"Desconocido","sector":"游닍 Otros","fob":52.45484,"cif":0,"peso":1.47605},{"fecha":"2014-12-01","cod":"0604900000","label":"Desconocido","sector":"游닍 Otros","fob":0.13554,"cif":0,"peso":0.018},{"fecha":"2014-12-01","cod":"0803901100","label":"Tipo 춺cavendish valery췉","sector":"游꼛 Frutas","fob":15207.0477,"cif":0,"peso":33605.94472},{"fecha":"2014-12-01","cod":"0803901200","label":"Bocadillo","sector":"游꼛 Frutas","fob":147.568,"cif":0,"peso":166.8336},{"fecha":"2014-12-01","cod":"0811909900","label":"Desconocido","sector":"游꼛 Frutas","fob":20.48,"cif":0,"peso":24.0},{"fecha":"2014-12-01","cod":"1404909000","label":"Desconocido","sector":"游닍 Otros","fob":29.5205,"cif":0,"peso":24.95},{"fecha":"2014-12-01","cod":"2007999200","label":"Pur칠s y pastas","sector":"游닍 Otros","fob":20.2728,"cif":0,"peso":38.4},{"fecha":"2014-12-01","cod":"2009892000","label":"De maracuy치","sector":"游닍 Otros","fob":100.125,"cif":0,"peso":12.5},{"fecha":"2014-12-01","cod":"2301201100","label":"Con un contenido de grasa superior a 2% en peso","sector":"游닍 Otros","fob":3665.3095,"cif":0,"peso":1642.084},{"fecha":"2014-12-01","cod":"2603000000","label":"Minerales de cobre y sus concentrados.","sector":"游닍 Otros","fob":2586.7017,"cif":0,"peso":1488.527},{"fecha":"2014-12-01","cod":"2616901000","label":"Minerales de oro y sus concentrados","sector":"游닍 Otros","fob":2919.51863,"cif":0,"peso":2491.251},{"fecha":"2014-12-01","cod":"3808919900","label":"Desconocido","sector":"游닍 Otros","fob":69.39,"cif":0,"peso":3.0},{"fecha":"2014-12-01","cod":"3915100000","label":"De pol칤meros de etileno","sector":"游빖 Pl치sticos","fob":236.94809,"cif":0,"peso":426.201},{"fecha":"2014-12-01","cod":"3915900090","label":"Desconocido","sector":"游빖 Pl치sticos","fob":221.73396,"cif":0,"peso":482.833},{"fecha":"2014-12-01","cod":"3921199000","label":"Desconocido","sector":"游빖 Pl치sticos","fob":10.929,"cif":0,"peso":72.86},{"fecha":"2014-12-01","cod":"4102100000","label":"Con lana","sector":"游닍 Otros","fob":9.724,"cif":0,"peso":14.22},{"fecha":"2014-12-01","cod":"4403990000","label":"Desconocido","sector":"游뿻 Madera","fob":99.37915,"cif":0,"peso":1513.22},{"fecha":"2014-12-01","cod":"4407220000","label":"Virola, imbuia y balsa","sector":"游뿻 Madera","fob":4124.65771,"cif":0,"peso":1319.713648},{"fecha":"2014-12-01","cod":"4408900000","label":"Desconocido","sector":"游뿻 Madera","fob":118.64875,"cif":0,"peso":28.26144},{"fecha":"2014-12-01","cod":"4413000000","label":"Madera densificada en bloques, tablas, tiras o perfiles.","sector":"游뿻 Madera","fob":30.9417,"cif":0,"peso":57.52},{"fecha":"2014-12-01","cod":"5305001100","label":"En bruto","sector":"游닍 Otros","fob":147.5,"cif":0,"peso":100.0},{"fecha":"2014-12-01","cod":"7404000000","label":"Desperdicios y desechos, de cobre.","sector":"游닍 Otros","fob":225.86259,"cif":0,"peso":41.778},{"fecha":"2014-12-01","cod":"7602000000","label":"Desperdicios y desechos, de aluminio.","sector":"游닍 Otros","fob":180.31,"cif":0,"peso":200.0},{"fecha":"2014-12-01","cod":"7616999000","label":"Desconocido","sector":"游닍 Otros","fob":6.65,"cif":0,"peso":8.13},{"fecha":"2014-12-01","cod":"7902000000","label":"Desperdicios y desechos, de cinc.","sector":"游닍 Otros","fob":39.68028,"cif":0,"peso":26.811},{"fecha":"2014-12-01","cod":"8301401000","label":"Para cajas de caudales","sector":"游닍 Otros","fob":97.4,"cif":0,"peso":3.15852},{"fecha":"2014-12-01","cod":"8301409000","label":"Desconocido","sector":"游닍 Otros","fob":47.5,"cif":0,"peso":0.7054},{"fecha":"2014-12-01","cod":"8504343000","label":"De potencia superior a 10.000 kva","sector":"游댋 El칠ctrico","fob":640.9852,"cif":0,"peso":57.0},{"fecha":"2014-12-01","cod":"8707100000","label":"De veh칤culos de la partida 87.03","sector":"游뚱 Veh칤culos","fob":35.0,"cif":0,"peso":1.69293},{"fecha":"2014-12-01","cod":"9401200000","label":"Asientos del tipo de los utilizados en veh칤culos autom칩viles","sector":"游닍 Otros","fob":39.59475,"cif":0,"peso":1.69292},{"fecha":"2014-12-01","cod":"9606301000","label":"De pl치stico o de tagua","sector":"游닍 Otros","fob":170.3648,"cif":0,"peso":18.764}]